CHANGES.txt
README.txt
opencore.js-configure.zcml
setup.py
oc_js.egg-info/PKG-INFO
oc_js.egg-info/SOURCES.txt
oc_js.egg-info/dependency_links.txt
oc_js.egg-info/entry_points.txt
oc_js.egg-info/namespace_packages.txt
oc_js.egg-info/not-zip-safe
oc_js.egg-info/requires.txt
oc_js.egg-info/top_level.txt
opencore/__init__.py
opencore/js/__init__.py
opencore/js/configure.zcml
opencore/js/oc-js/checkbox-limit-select.js
opencore/js/oc-js/delete_list.js
opencore/js/oc-js/oc-behaviors.js
opencore/js/thirdparty/jquery/jquery-1.3.2.min.js
opencore/js/thirdparty/jquery/jquery.timers-1.1.2.js
opencore/js/thirdparty/xinha/Xinha.css
opencore/js/thirdparty/xinha/XinhaCore.js
opencore/js/thirdparty/xinha/htmlarea.js
opencore/js/thirdparty/xinha/license.txt
opencore/js/thirdparty/xinha/release-notes.txt
opencore/js/thirdparty/xinha/xinhaconfig.js
opencore/js/thirdparty/xinha/contrib/compress.bat
opencore/js/thirdparty/xinha/contrib/compress.php
opencore/js/thirdparty/xinha/contrib/compression_readme.txt
opencore/js/thirdparty/xinha/contrib/dojo_js_compressor.jar
opencore/js/thirdparty/xinha/contrib/lc_parse_strings.php
opencore/js/thirdparty/xinha/contrib/php-xinha.php
opencore/js/thirdparty/xinha/examples/Extended.html
opencore/js/thirdparty/xinha/examples/custom.css
opencore/js/thirdparty/xinha/examples/dynamic.css
opencore/js/thirdparty/xinha/examples/ext_example-body.html
opencore/js/thirdparty/xinha/examples/ext_example-dest.php
opencore/js/thirdparty/xinha/examples/ext_example-menu.php
opencore/js/thirdparty/xinha/examples/ext_example.html
opencore/js/thirdparty/xinha/examples/full_example.css
opencore/js/thirdparty/xinha/examples/full_example.js
opencore/js/thirdparty/xinha/examples/simple_example.html
opencore/js/thirdparty/xinha/examples/stylist.css
opencore/js/thirdparty/xinha/examples/testbed.html
opencore/js/thirdparty/xinha/images/ed_about.gif
opencore/js/thirdparty/xinha/images/ed_align.gif
opencore/js/thirdparty/xinha/images/ed_align_center.gif
opencore/js/thirdparty/xinha/images/ed_align_justify.gif
opencore/js/thirdparty/xinha/images/ed_align_left.gif
opencore/js/thirdparty/xinha/images/ed_align_right.gif
opencore/js/thirdparty/xinha/images/ed_blank.gif
