Metadata-Version: 1.0
Name: oc-js
Version: 0.7
Summary: javascript and zcml registrations required for opencore
Home-page: http://www.openplans.org/projects/opencore
Author: opencore dev team
Author-email: opencore-dev@lists.openplans.org
License: GPL
Keywords: javascript zcml
Platform: UNKNOWN
Classifier: Framework :: Zope3
Classifier: Framework :: YUI-ext
Classifier: Programming Language :: Javascript
Classifier: Topic :: Software Development :: Libraries :: Python Modules
